akulaku/__init__.py
akulaku/exceptions.py
akulaku/gateway.py
akulaku/helpers.py
akulaku/models.py
akulaku-0.1.dist-info/METADATA
akulaku-0.1.dist-info/WHEEL
akulaku-0.1.dist-info/top_level.txt
akulaku-0.1.dist-info/RECORD
