Metadata-Version: 2.1
Name: akulaku
Version: 0.1
Summary: UNKNOWN
Home-page: UNKNOWN
Author: PT Gramedia Digital Nusantara
Author-email: UNKNOWN
License: UNKNOWN
Platform: UNKNOWN
Requires-Dist: requests (<3.0,>=2.21.0)
